[ {
  "description" : "description",
  "entity.guid" : "OBFUSCATED",
  "entity.name" : "native-otlp-test",
  "entity.type" : "SERVICE",
  "instrumentation.provider" : "opentelemetry",
  "message_id" : "OBFUSCATED",
  "metricName" : "my_int_histogram",
  "my_int_histogram" : {
    "buckets" : 320,
    "count" : 11,
    "max" : 3.0,
    "min" : 1.0,
    "sum" : 100.0,
    "type" : "distribution"
  },
  "newrelic.source" : "api.metrics.otlp",
  "otel.library.name" : "my-instrumentation-library",
  "otel.library.version" : "foo",
  "resource_barrkey" : [ true, false ],
  "resource_bkey" : true,
  "resource_darrkey" : [ 1.0, 2.0 ],
  "resource_dkey" : 1.0,
  "resource_iarrkey" : [ 1, 2 ],
  "resource_ikey" : 1,
  "resource_sarrkey" : [ "value1", "value2" ],
  "resource_skey" : "value",
  "service.name" : "native-otlp-test",
  "skey" : "value",
  "timestamp" : 0,
  "unit" : "unit"
} ]